ruff_format-0.3.0.dist-info/METADATA
ruff_format-0.3.0.dist-info/WHEEL
ruff_format-0.3.0.dist-info/licenses/LICENSE
ruff_format/__init__.py
ruff_format/__init__.pyi
ruff_format/py.typed
ruff_format/ruff_format.pypy310-pp73-aarch64-linux-gnu.so
ruff_format-0.3.0.dist-info/RECORD
